mend_sca_cleanup_tool/__init__.py
mend_sca_cleanup_tool/_version.py
mend_sca_cleanup_tool/sca_cleanup_tool.py
mend_sca_cleanup_tool-24.6.4.dist-info/LICENSE
mend_sca_cleanup_tool-24.6.4.dist-info/METADATA
mend_sca_cleanup_tool-24.6.4.dist-info/WHEEL
mend_sca_cleanup_tool-24.6.4.dist-info/entry_points.txt
mend_sca_cleanup_tool-24.6.4.dist-info/top_level.txt
mend_sca_cleanup_tool-24.6.4.dist-info/RECORD
