Metadata-Version: 2.1
Name: mend-sca-cleanup-tool
Version: 24.6.4
Summary: Mend SCA Cleanup Tool
Home-page: https://github.com/mend-toolkit/mend-sca-cleanup-tool
Author: Mend Professional Services
Author-email: ps@whitesourcesoftware.com
License: LICENSE.txt
Classifier: Programming Language :: Python :: 3.9
Classifier: Programming Language :: Python :: 3.10
Classifier: Programming Language :: Python :: 3.11
Classifier: License :: OSI Approved :: Apache Software License
Classifier: Operating System :: OS Independent
Requires-Python: >=3.9
License-File: LICENSE
Requires-Dist: configparser==5.3.0
Requires-Dist: DateTime~=4.3
Requires-Dist: setuptools==68.2.2
Requires-Dist: requests~=2.31.0
